LICENSE.txt
README.rst
setup.py
argtoolbox/__init__.py
argtoolbox/argtoolbox.py
argtoolbox/commands.py
argtoolbox.egg-info/PKG-INFO
argtoolbox.egg-info/SOURCES.txt
argtoolbox.egg-info/dependency_links.txt
argtoolbox.egg-info/entry_points.txt
argtoolbox.egg-info/requires.txt
argtoolbox.egg-info/top_level.txt
argtoolbox/templates/default.tml
tests/tests.py