Metadata-Version: 2.1
Name: argtoolbox
Version: 1.1.5
Summary: The easy way to create a short program with file options and command line options.
Home-page: https://github.com/fred49/argtoolbox
Author: Frederic MARTIN
Author-email: frederic.martin.fma@gmail.com
License: GPL3
Keywords: argparse ConfigFile command line interface
Classifier: Development Status :: 4 - Beta
Classifier: Intended Audience :: Developers
Classifier: Topic :: Software Development :: Build Tools
Classifier: Environment :: Console
Classifier: License :: OSI Approved :: GNU General Public License v3 (GPLv3)
Classifier: Programming Language :: Python :: 3
License-File: LICENSE.txt
